setup.py
bin/pymntos
pymntos/__init__.py
pymntos/conduct.py
pymntos/meetup.py
pymntos.egg-info/PKG-INFO
pymntos.egg-info/SOURCES.txt
pymntos.egg-info/dependency_links.txt
pymntos.egg-info/requires.txt
pymntos.egg-info/top_level.txt