Metadata-Version: 1.0
Name: pymntos
Version: 0.2
Summary: PyMNtos library
Home-page: http://bitbucket.org/wyattwalter/pymntos-lib
Author: Wyatt Walter
Author-email: wyattwalter@gmail.com
License: MIT
Platform: UNKNOWN
